<configuration><instance>0<vehicles><primary_vehicle_amount>4</primary_vehicle_amount><secondary_vehicle_amount>9</secondary_vehicle_amount></vehicles><graph><size>100</size><vertex_amount>5<vertex><number>0</number><x>54.88135039273247</x><y>71.51893663724195</y><demand>0</demand><mode_amount>1</mode_amount></vertex><vertex><number>1</number><x>79.17250380826646</x><y>52.88949197529045</y><demand>44</demand><mode_amount>3</mode_amount></vertex><vertex><number>2</number><x>14.33532874090464</x><y>94.46689170495839</y><demand>30</demand><mode_amount>2</mode_amount></vertex><vertex><number>3</number><x>69.76311959272648</x><y>6.022547162926983</y><demand>23</demand><mode_amount>4</mode_amount></vertex><vertex><number>4</number><x>46.63107728563063</x><y>24.442559200160275</y><demand>43</demand><mode_amount>3</mode_amount></vertex><vertex><number>5</number><x>1.9987665408758737</x><y>44.17109212488454</y><demand>31</demand><mode_amount>4</mode_amount></vertex></vertex_amount></graph></instance><instance>1<vehicles><primary_vehicle_amount>4</primary_vehicle_amount><secondary_vehicle_amount>9</secondary_vehicle_amount></vehicles><graph><size>100</size><vertex_amount>5<vertex><number>0</number><x>60.276337607164386</x><y>54.48831829968969</y><demand>0</demand><mode_amount>1</mode_amount></vertex><vertex><number>1</number><x>92.5596638292661</x><y>7.103605819788694</y><demand>29</demand><mode_amount>2</mode_amount></vertex><vertex><number>2</number><x>47.360041934665745</x><y>18.633234332675997</y><demand>38</demand><mode_amount>2</mode_amount></vertex><vertex><number>3</number><x>67.06378696181594</x><y>21.03825610738409</y><demand>47</demand><mode_amount>2</mode_amount></vertex><vertex><number>4</number><x>67.47523222590208</x><y>31.720174206929606</y><demand>25</demand><mode_amount>3</mode_amount></vertex><vertex><number>5</number><x>35.94444639693215</x><y>48.08935308361628</y><demand>45</demand><mode_amount>4</mode_amount></vertex></vertex_amount></graph></instance><instance>2<vehicles><primary_vehicle_amount>4</primary_vehicle_amount><secondary_vehicle_amount>9</secondary_vehicle_amount></vehicles><graph><size>100</size><vertex_amount>5<vertex><number>0</number><x>42.36547993389047</x><y>64.58941130666561</y><demand>0</demand><mode_amount>1</mode_amount></vertex><vertex><number>1</number><x>2.021839744032572</x><y>83.2619845547938</y><demand>35</demand><mode_amount>2</mode_amount></vertex><vertex><number>2</number><x>56.84339488686485</x><y>1.8789800436355142</y><demand>41</demand><mode_amount>3</mode_amount></vertex><vertex><number>3</number><x>31.542835092418386</x><y>36.37107709426226</y><demand>45</demand><mode_amount>4</mode_amount></vertex><vertex><number>4</number><x>94.95710534507421</x><y>66.25268669500443</y><demand>20</demand><mode_amount>3</mode_amount></vertex><vertex><number>5</number><x>88.04758892525955</x><y>91.82354663621447</y><demand>23</demand><mode_amount>4</mode_amount></vertex></vertex_amount></graph></instance><instance>3<vehicles><primary_vehicle_amount>4</primary_vehicle_amount><secondary_vehicle_amount>9</secondary_vehicle_amount></vehicles><graph><size>100</size><vertex_amount>5<vertex><number>0</number><x>43.75872112626925</x><y>89.17730007820798</y><demand>0</demand><mode_amount>1</mode_amount></vertex><vertex><number>1</number><x>97.8618342232764</x><y>79.91585642167236</y><demand>39</demand><mode_amount>3</mode_amount></vertex><vertex><number>2</number><x>61.20957227224214</x><y>61.69339968747569</y><demand>35</demand><mode_amount>2</mode_amount></vertex><vertex><number>3</number><x>43.86015134623204</x><y>98.83738380592261</y><demand>24</demand><mode_amount>2</mode_amount></vertex><vertex><number>4</number><x>83.7944907498804</x><y>9.609840789396307</y><demand>49</demand><mode_amount>4</mode_amount></vertex><vertex><number>5</number><x>56.51888666048753</x><y>86.5102561305385</y><demand>38</demand><mode_amount>4</mode_amount></vertex></vertex_amount></graph></instance><instance>4<vehicles><primary_vehicle_amount>4</primary_vehicle_amount><secondary_vehicle_amount>9</secondary_vehicle_amount></vehicles><graph><size>100</size><vertex_amount>5<vertex><number>0</number><x>96.36627605010293</x><y>38.34415188257777</y><demand>0</demand><mode_amount>1</mode_amount></vertex><vertex><number>1</number><x>78.05291762864555</x><y>11.827442586893323</y><demand>20</demand><mode_amount>3</mode_amount></vertex><vertex><number>2</number><x>68.18202991034835</x><y>35.9507900573786</y><demand>44</demand><mode_amount>3</mode_amount></vertex><vertex><number>3</number><x>16.130951788499626</x><y>65.31083254653984</y><demand>28</demand><mode_amount>4</mode_amount></vertex><vertex><number>4</number><x>50.96243767199001</x><y>5.5714693701606315</y><demand>41</demand><mode_amount>3</mode_amount></vertex><vertex><number>5</number><x>9.394051075844168</x><y>57.59464955561793</y><demand>30</demand><mode_amount>4</mode_amount></vertex></vertex_amount></graph></instance></configuration>